Metrik/__init__.py
Metrik/fast_app.py
Metrik/main.py
Metrik/exceptions/ObjectDoesNotExists.py
Metrik/exceptions/__init__.py
Metrik/models/ORMModel.py
Metrik/models/OrmManager.py
Metrik/models/Ticket.py
Metrik/models/__init__.py
Metrik/utils/__init__.py
Metrik/utils/sql_helper.py
PandaPosMetrik-2.1.0.dist-info/METADATA
PandaPosMetrik-2.1.0.dist-info/WHEEL
PandaPosMetrik-2.1.0.dist-info/top_level.txt
PandaPosMetrik-2.1.0.dist-info/RECORD
