Metadata-Version: 2.1
Name: PandaPosMetrik
Version: 2.1.0
Requires-Dist: pyodbc
